{
  "id": "camera-follow",
  "kind": "asset",
  "version": "1.0.0",
  "category": "world",
  "tags": ["world", "camera", "follow"],
  "license": "MIT",
  "description": "Camera preset: follow a tagged entity with optional smoothing and deadzone (platformers, top-down explorers). A host hint consumed by the page that owns the canvas; registers no runtime type.",
  "dependencies": [],
  "definition": {
    "type": "camera-follow",
    "params": { "mode": "follow", "targetTag": "player", "smoothing": 0.12, "deadzone": { "w": 80, "h": 60 } }
  }
}
